{
  "/dashboard/infants/[id]/vaccinations/page": "app/dashboard/infants/[id]/vaccinations/page.js",
  "/dashboard/infants/[id]/calendar/page": "app/dashboard/infants/[id]/calendar/page.js",
  "/dashboard/infants/[id]/page": "app/dashboard/infants/[id]/page.js",
  "/dashboard/infants/[id]/progress/page": "app/dashboard/infants/[id]/progress/page.js",
  "/dashboard/infants/[id]/insights/page": "app/dashboard/infants/[id]/insights/page.js",
  "/dashboard/infants/[id]/tracker/page": "app/dashboard/infants/[id]/tracker/page.js",
  "/dashboard/infants/[id]/growth/page": "app/dashboard/infants/[id]/growth/page.js"
}